torchcde/__init__.py
torchcde/interpolation_base.py
torchcde/interpolation_cubic.py
torchcde/interpolation_hermite_cubic_bdiff.py
torchcde/interpolation_linear.py
torchcde/log_ode.py
torchcde/misc.py
torchcde/solver.py
torchcde-0.2.5.dist-info/LICENSE
torchcde-0.2.5.dist-info/METADATA
torchcde-0.2.5.dist-info/WHEEL
torchcde-0.2.5.dist-info/top_level.txt
torchcde-0.2.5.dist-info/RECORD
