Metadata-Version: 2.1
Name: torchcde
Version: 0.2.5
Summary: Differentiable controlled differential equation solvers for PyTorch with GPU support and memory-efficient adjoint backpropagation.
Home-page: https://github.com/patrick-kidger/torchcde
Author: Patrick Kidger
Author-email: contact@kidger.site
Maintainer: Patrick Kidger
Maintainer-email: contact@kidger.site
License: Apache-2.0
Platform: UNKNOWN
Classifier: Development Status :: 4 - Beta
Classifier: Intended Audience :: Developers
Classifier: Intended Audience :: Financial and Insurance Industry
Classifier: Intended Audience :: Information Technology
Classifier: Intended Audience :: Science/Research
Classifier: License :: OSI Approved :: Apache Software License
Classifier: Natural Language :: English
Classifier: Operating System :: MacOS :: MacOS X
Classifier: Operating System :: Microsoft :: Windows
Classifier: Operating System :: Unix
Classifier: Programming Language :: Python :: 3
Classifier: Programming Language :: Python :: Implementation :: CPython
Classifier: Topic :: Scientific/Engineering :: Artificial Intelligence
Classifier: Topic :: Scientific/Engineering :: Information Analysis
Classifier: Topic :: Scientific/Engineering :: Mathematics
Requires-Python: ~=3.6
Requires-Dist: torch (>=1.7.0)
Requires-Dist: torchdiffeq (>=0.2.0)
Requires-Dist: torchsde (>=0.2.5)
